MANIFEST.in
README.txt
bootstrap.py
buildout.cfg
deploy.ini
setup.py
zinebuildout/__init__.py
zinebuildout/paste.py
zinebuildout/tweets.html
zinebuildout/twitter_widget.py
zinebuildout.egg-info/PKG-INFO
zinebuildout.egg-info/SOURCES.txt
zinebuildout.egg-info/dependency_links.txt
zinebuildout.egg-info/entry_points.txt
zinebuildout.egg-info/not-zip-safe
zinebuildout.egg-info/requires.txt
zinebuildout.egg-info/top_level.txt