Metadata-Version: 1.0
Name: zinebuildout
Version: 0.6.1
Summary: Deploy the Zine blog engine with Paste in a buildout
Home-page: https://cody.gorfou.fr/hg/zinebuildout
Author: Christophe Combelles
Author-email: ccomb@gorfou.fr
License: BSD
Keywords: zine buildout paste
Platform: UNKNOWN
Classifier: Programming Language :: Python
Classifier: Environment :: Web Environment
Classifier: Topic :: Internet :: WWW/HTTP :: WSGI :: Application
Classifier: Intended Audience :: Information Technology
Classifier: Framework :: Buildout
Classifier: Framework :: Paste
Classifier: License :: OSI Approved :: BSD License
